{
  "generatedAt": "2026-07-09",
  "policy": {
    "noInventedData": true,
    "missingUnavailableStats": null
  },
  "matches": {
    "france-morocco-2026-07-09": {
      "match": "France-Morocco",
      "teams": {
        "France": {
          "displayName": "Francia",
          "sourcePlayerStats": "data/player-stats/france-morocco-2026-07-09.json",
          "rawMatches": [
            {
              "matchId": "france-senegal-2026-06-16",
              "match": "France vs Senegal",
              "opponent": "Senegal",
              "round": "Group stage",
              "matchContext": {
                "tipoPartita": "girone",
                "livelloAvversario": "medio-alto",
                "statoAvversario": "fisica, verticale, intensa",
                "statoGara": "Francia concreta contro avversario atletico",
                "pesoModello": 0.82
              },
              "goalsFor": 3,
              "goalsAgainst": 1,
              "shotsFor": 11,
              "shotsAgainst": 6,
              "shotsOnTargetFor": 8,
              "shotsOnTargetAgainst": 2,
              "cornersFor": null,
              "cornersAgainst": null,
              "foulsCommitted": 5,
              "foulsDrawn": 8,
              "yellowCards": 0,
              "redCards": 0,
              "possession": null,
              "offsides": null,
              "saves": null,
              "cleanSheets": 0,
              "firstHalfGoalsFor": null,
              "firstHalfGoalsAgainst": null,
              "secondHalfGoalsFor": null,
              "secondHalfGoalsAgainst": null
            },
            {
              "matchId": "france-iraq-2026-06-22",
              "match": "France vs Iraq",
              "opponent": "Iraq",
              "round": "Group stage",
              "matchContext": {
                "tipoPartita": "girone facile con turnover",
                "livelloAvversario": "basso-medio",
                "statoAvversario": "difensiva, diretta",
                "statoGara": "Francia dominante, meno predittiva",
                "pesoModello": 0.55
              },
              "goalsFor": 3,
              "goalsAgainst": 0,
              "shotsFor": 19,
              "shotsAgainst": 4,
              "shotsOnTargetFor": 5,
              "shotsOnTargetAgainst": 0,
              "cornersFor": null,
              "cornersAgainst": null,
              "foulsCommitted": 8,
              "foulsDrawn": 4,
              "yellowCards": 0,
              "redCards": 0,
              "possession": null,
              "offsides": null,
              "saves": null,
              "cleanSheets": 1,
              "firstHalfGoalsFor": null,
              "firstHalfGoalsAgainst": null,
              "secondHalfGoalsFor": null,
              "secondHalfGoalsAgainst": null
            },
            {
              "matchId": "norway-france-2026-06-26",
              "match": "Norway vs France",
              "opponent": "Norway",
              "round": "Group stage",
              "matchContext": {
                "tipoPartita": "girone contro avversario forte",
                "livelloAvversario": "alto",
                "statoAvversario": "fisica, verticale",
                "statoGara": "gara aperta contro avversario forte",
                "pesoModello": 0.78
              },
              "goalsFor": 4,
              "goalsAgainst": 1,
              "shotsFor": 18,
              "shotsAgainst": 10,
              "shotsOnTargetFor": 9,
              "shotsOnTargetAgainst": 4,
              "cornersFor": null,
              "cornersAgainst": null,
              "foulsCommitted": 11,
              "foulsDrawn": 8,
              "yellowCards": 1,
              "redCards": 0,
              "possession": null,
              "offsides": null,
              "saves": null,
              "cleanSheets": 0,
              "firstHalfGoalsFor": null,
              "firstHalfGoalsAgainst": null,
              "secondHalfGoalsFor": null,
              "secondHalfGoalsAgainst": null
            },
            {
              "matchId": "france-sweden-2026-06-30",
              "match": "France vs Sweden",
              "opponent": "Sweden",
              "round": "Round of 32",
              "matchContext": {
                "tipoPartita": "eliminazione diretta",
                "livelloAvversario": "medio-alto",
                "statoAvversario": "fisica, compatta",
                "statoGara": "Francia dominante in knockout",
                "pesoModello": 0.82
              },
              "goalsFor": 3,
              "goalsAgainst": 0,
              "shotsFor": 25,
              "shotsAgainst": 8,
              "shotsOnTargetFor": 12,
              "shotsOnTargetAgainst": 3,
              "cornersFor": null,
              "cornersAgainst": null,
              "foulsCommitted": 14,
              "foulsDrawn": 9,
              "yellowCards": 0,
              "redCards": 0,
              "possession": null,
              "offsides": null,
              "saves": null,
              "cleanSheets": 1,
              "firstHalfGoalsFor": null,
              "firstHalfGoalsAgainst": null,
              "secondHalfGoalsFor": null,
              "secondHalfGoalsAgainst": null
            },
            {
              "matchId": "paraguay-france-2026-07-04",
              "match": "Paraguay vs France",
              "opponent": "Paraguay",
              "round": "Round of 16",
              "matchContext": {
                "tipoPartita": "eliminazione diretta",
                "livelloAvversario": "medio",
                "statoAvversario": "difensiva, fisica, blocco basso",
                "statoGara": "partita chiusa contro squadra compatta",
                "pesoModello": 0.95
              },
              "goalsFor": 1,
              "goalsAgainst": 0,
              "shotsFor": 15,
              "shotsAgainst": 5,
              "shotsOnTargetFor": 5,
              "shotsOnTargetAgainst": 0,
              "cornersFor": null,
              "cornersAgainst": null,
              "foulsCommitted": 11,
              "foulsDrawn": 13,
              "yellowCards": 3,
              "redCards": 0,
              "possession": null,
              "offsides": null,
              "saves": null,
              "cleanSheets": 1,
              "firstHalfGoalsFor": null,
              "firstHalfGoalsAgainst": null,
              "secondHalfGoalsFor": null,
              "secondHalfGoalsAgainst": null
            }
          ],
          "teamWeightedModel": {
            "matches": 5,
            "weightedGoalsForPerMatch": 2.71,
            "weightedGoalsAgainstPerMatch": 0.41,
            "weightedShotsForPerMatch": 17.41,
            "weightedShotsAgainstPerMatch": 6.69,
            "weightedShotsOnTargetForPerMatch": 7.89,
            "weightedShotsOnTargetAgainstPerMatch": 1.84,
            "weightedCornersForPerMatch": null,
            "weightedCornersAgainstPerMatch": null,
            "disciplineIndex": 63,
            "attackIndex": 100,
            "defenseIndex": 71,
            "cornerIndex": null,
            "tempoIndex": 80,
            "pressureIndex": 78
          },
          "trends": {
            "lastTwoMatches": {
              "shotsForPerMatch": 20,
              "shotsOnTargetForPerMatch": 8.5,
              "foulsCommittedPerMatch": 12.5,
              "yellowCardsPerMatch": 1.5
            },
            "knockout": {
              "matches": 2,
              "shotsForPerMatch": 20,
              "shotsOnTargetForPerMatch": 8.5,
              "foulsCommittedPerMatch": 12.5,
              "yellowCardsPerMatch": 1.5
            }
          },
          "missingFields": [
            "cornersFor",
            "cornersAgainst",
            "possession",
            "saves",
            "firstHalfGoalsFor",
            "firstHalfGoalsAgainst",
            "secondHalfGoalsFor",
            "secondHalfGoalsAgainst"
          ]
        },
        "Morocco": {
          "displayName": "Marocco",
          "sourcePlayerStats": "data/player-stats/france-morocco-2026-07-09.json",
          "rawMatches": [
            {
              "matchId": "brazil-morocco-2026-06-13",
              "match": "Brazil vs Morocco",
              "opponent": "Brazil",
              "round": "Group stage",
              "matchContext": {
                "tipoPartita": "girone contro avversario forte",
                "livelloAvversario": "elite",
                "statoAvversario": "tecnica, alto talento offensivo",
                "statoGara": "Marocco competitivo contro big",
                "pesoModello": 0.95
              },
              "goalsFor": 1,
              "goalsAgainst": 1,
              "shotsFor": 14,
              "shotsAgainst": 12,
              "shotsOnTargetFor": 3,
              "shotsOnTargetAgainst": 5,
              "cornersFor": null,
              "cornersAgainst": null,
              "foulsCommitted": 14,
              "foulsDrawn": 16,
              "yellowCards": 0,
              "redCards": 0,
              "possession": null,
              "offsides": null,
              "saves": null,
              "cleanSheets": 0,
              "firstHalfGoalsFor": null,
              "firstHalfGoalsAgainst": null,
              "secondHalfGoalsFor": null,
              "secondHalfGoalsAgainst": null
            },
            {
              "matchId": "scotland-morocco-2026-06-19",
              "match": "Scotland vs Morocco",
              "opponent": "Scotland",
              "round": "Group stage",
              "matchContext": {
                "tipoPartita": "girone",
                "livelloAvversario": "medio",
                "statoAvversario": "fisica, diretta, compatta",
                "statoGara": "Marocco avanti e in controllo",
                "pesoModello": 0.62
              },
              "goalsFor": 1,
              "goalsAgainst": 0,
              "shotsFor": 12,
              "shotsAgainst": 6,
              "shotsOnTargetFor": 2,
              "shotsOnTargetAgainst": 0,
              "cornersFor": null,
              "cornersAgainst": null,
              "foulsCommitted": 8,
              "foulsDrawn": 10,
              "yellowCards": 1,
              "redCards": 0,
              "possession": null,
              "offsides": null,
              "saves": null,
              "cleanSheets": 1,
              "firstHalfGoalsFor": null,
              "firstHalfGoalsAgainst": null,
              "secondHalfGoalsFor": null,
              "secondHalfGoalsAgainst": null
            },
            {
              "matchId": "morocco-haiti-2026-06-24",
              "match": "Morocco vs Haiti",
              "opponent": "Haiti",
              "round": "Group stage",
              "matchContext": {
                "tipoPartita": "girone facile con turnover",
                "livelloAvversario": "basso-medio",
                "statoAvversario": "aperta e meno organizzata",
                "statoGara": "gara meno predittiva",
                "pesoModello": 0.45
              },
              "goalsFor": 4,
              "goalsAgainst": 1,
              "shotsFor": 22,
              "shotsAgainst": 9,
              "shotsOnTargetFor": 11,
              "shotsOnTargetAgainst": 2,
              "cornersFor": null,
              "cornersAgainst": null,
              "foulsCommitted": 10,
              "foulsDrawn": 18,
              "yellowCards": 0,
              "redCards": 0,
              "possession": null,
              "offsides": null,
              "saves": null,
              "cleanSheets": 0,
              "firstHalfGoalsFor": null,
              "firstHalfGoalsAgainst": null,
              "secondHalfGoalsFor": null,
              "secondHalfGoalsAgainst": null
            },
            {
              "matchId": "netherlands-morocco-2026-06-29",
              "match": "Netherlands vs Morocco",
              "opponent": "Netherlands",
              "round": "Round of 32",
              "matchContext": {
                "tipoPartita": "eliminazione diretta",
                "livelloAvversario": "alto",
                "statoAvversario": "tecnica, possesso, qualita",
                "statoGara": "gara equilibrata decisa ai rigori",
                "pesoModello": 1
              },
              "goalsFor": 1,
              "goalsAgainst": 1,
              "shotsFor": 11,
              "shotsAgainst": 6,
              "shotsOnTargetFor": 5,
              "shotsOnTargetAgainst": 2,
              "cornersFor": null,
              "cornersAgainst": null,
              "foulsCommitted": 15,
              "foulsDrawn": 15,
              "yellowCards": 1,
              "redCards": 0,
              "possession": null,
              "offsides": null,
              "saves": null,
              "cleanSheets": 0,
              "firstHalfGoalsFor": null,
              "firstHalfGoalsAgainst": null,
              "secondHalfGoalsFor": null,
              "secondHalfGoalsAgainst": null
            },
            {
              "matchId": "canada-morocco-2026-07-04",
              "match": "Canada vs Morocco",
              "opponent": "Canada",
              "round": "Round of 16",
              "matchContext": {
                "tipoPartita": "eliminazione diretta",
                "livelloAvversario": "medio",
                "statoAvversario": "fisica, diretta",
                "statoGara": "Marocco dominante e in gestione",
                "pesoModello": 0.82
              },
              "goalsFor": 3,
              "goalsAgainst": 0,
              "shotsFor": 5,
              "shotsAgainst": 10,
              "shotsOnTargetFor": 4,
              "shotsOnTargetAgainst": 3,
              "cornersFor": null,
              "cornersAgainst": null,
              "foulsCommitted": 14,
              "foulsDrawn": 23,
              "yellowCards": 4,
              "redCards": 0,
              "possession": null,
              "offsides": null,
              "saves": null,
              "cleanSheets": 1,
              "firstHalfGoalsFor": null,
              "firstHalfGoalsAgainst": null,
              "secondHalfGoalsFor": null,
              "secondHalfGoalsAgainst": null
            }
          ],
          "teamWeightedModel": {
            "matches": 5,
            "weightedGoalsForPerMatch": 1.78,
            "weightedGoalsAgainstPerMatch": 0.63,
            "weightedShotsForPerMatch": 11.91,
            "weightedShotsAgainstPerMatch": 8.69,
            "weightedShotsOnTargetForPerMatch": 4.51,
            "weightedShotsOnTargetAgainstPerMatch": 2.63,
            "weightedCornersForPerMatch": null,
            "weightedCornersAgainstPerMatch": null,
            "disciplineIndex": 51,
            "attackIndex": 62,
            "defenseIndex": 60,
            "cornerIndex": null,
            "tempoIndex": 69,
            "pressureIndex": 88
          },
          "trends": {
            "lastTwoMatches": {
              "shotsForPerMatch": 8,
              "shotsOnTargetForPerMatch": 4.5,
              "foulsCommittedPerMatch": 14.5,
              "yellowCardsPerMatch": 2.5
            },
            "knockout": {
              "matches": 2,
              "shotsForPerMatch": 8,
              "shotsOnTargetForPerMatch": 4.5,
              "foulsCommittedPerMatch": 14.5,
              "yellowCardsPerMatch": 2.5
            }
          },
          "missingFields": [
            "cornersFor",
            "cornersAgainst",
            "possession",
            "saves",
            "firstHalfGoalsFor",
            "firstHalfGoalsAgainst",
            "secondHalfGoalsFor",
            "secondHalfGoalsAgainst"
          ]
        }
      }
    },
    "spain-belgium-2026-07-10": {
      "match": "Spain-Belgium",
      "teams": {
        "Spain": {
          "displayName": "Spagna",
          "sourcePlayerStats": "data/player-stats/spain-belgium-2026-07-10.json",
          "rawMatches": [
            {
              "matchId": "spain-cape-verde-2026",
              "match": "Spain vs Cape Verde",
              "opponent": "Cape Verde",
              "round": "Group stage",
              "matchContext": {
                "tipoPartita": "girone facile con turnover",
                "livelloAvversario": "basso-medio",
                "statoAvversario": "molto difensivo, blocco basso",
                "statoGara": "Spagna dominante ma poco concreta",
                "pesoModello": 0.45
              },
              "goalsFor": 0,
              "goalsAgainst": 0,
              "shotsFor": 27,
              "shotsAgainst": 6,
              "shotsOnTargetFor": 7,
              "shotsOnTargetAgainst": 1,
              "cornersFor": null,
              "cornersAgainst": null,
              "foulsCommitted": 10,
              "foulsDrawn": 1,
              "yellowCards": 1,
              "redCards": 0,
              "possession": null,
              "offsides": null,
              "saves": null,
              "cleanSheets": 1,
              "firstHalfGoalsFor": null,
              "firstHalfGoalsAgainst": null,
              "secondHalfGoalsFor": null,
              "secondHalfGoalsAgainst": null
            },
            {
              "matchId": "spain-saudi-arabia-2026",
              "match": "Spain vs Saudi Arabia",
              "opponent": "Saudi Arabia",
              "round": "Group stage",
              "matchContext": {
                "tipoPartita": "girone",
                "livelloAvversario": "basso-medio",
                "statoAvversario": "difensivo, concede campo",
                "statoGara": "gara chiusa presto e dominata",
                "pesoModello": 0.6
              },
              "goalsFor": 3,
              "goalsAgainst": 0,
              "shotsFor": 22,
              "shotsAgainst": 3,
              "shotsOnTargetFor": 8,
              "shotsOnTargetAgainst": 1,
              "cornersFor": null,
              "cornersAgainst": null,
              "foulsCommitted": 10,
              "foulsDrawn": 1,
              "yellowCards": 0,
              "redCards": 0,
              "possession": null,
              "offsides": null,
              "saves": null,
              "cleanSheets": 1,
              "firstHalfGoalsFor": null,
              "firstHalfGoalsAgainst": null,
              "secondHalfGoalsFor": null,
              "secondHalfGoalsAgainst": null
            },
            {
              "matchId": "uruguay-spain-2026",
              "match": "Uruguay vs Spain",
              "opponent": "Uruguay",
              "round": "Group stage",
              "matchContext": {
                "tipoPartita": "girone contro avversario forte",
                "livelloAvversario": "alto",
                "statoAvversario": "fisico, aggressivo",
                "statoGara": "partita tesa e sporca",
                "pesoModello": 0.7
              },
              "goalsFor": 1,
              "goalsAgainst": 0,
              "shotsFor": 6,
              "shotsAgainst": 5,
              "shotsOnTargetFor": 1,
              "shotsOnTargetAgainst": 1,
              "cornersFor": null,
              "cornersAgainst": null,
              "foulsCommitted": 14,
              "foulsDrawn": 13,
              "yellowCards": 1,
              "redCards": 0,
              "possession": null,
              "offsides": null,
              "saves": null,
              "cleanSheets": 1,
              "firstHalfGoalsFor": null,
              "firstHalfGoalsAgainst": null,
              "secondHalfGoalsFor": null,
              "secondHalfGoalsAgainst": null
            },
            {
              "matchId": "spain-austria-2026-07-02",
              "match": "Spain vs Austria",
              "opponent": "Austria",
              "round": "Round of 32",
              "matchContext": {
                "tipoPartita": "eliminazione diretta",
                "livelloAvversario": "medio-alto",
                "statoAvversario": "fisico, organizzato",
                "statoGara": "Spagna dominante, vantaggio gestito",
                "pesoModello": 0.82
              },
              "goalsFor": 3,
              "goalsAgainst": 0,
              "shotsFor": 23,
              "shotsAgainst": 5,
              "shotsOnTargetFor": 10,
              "shotsOnTargetAgainst": 0,
              "cornersFor": null,
              "cornersAgainst": null,
              "foulsCommitted": 8,
              "foulsDrawn": 15,
              "yellowCards": 0,
              "redCards": 0,
              "possession": null,
              "offsides": null,
              "saves": null,
              "cleanSheets": 1,
              "firstHalfGoalsFor": null,
              "firstHalfGoalsAgainst": null,
              "secondHalfGoalsFor": null,
              "secondHalfGoalsAgainst": null
            },
            {
              "matchId": "portugal-spain-2026-07-06",
              "match": "Portugal vs Spain",
              "opponent": "Portugal",
              "round": "Round of 16",
              "matchContext": {
                "tipoPartita": "eliminazione diretta",
                "livelloAvversario": "elite",
                "statoAvversario": "tecnico, organizzato",
                "statoGara": "partita chiusa/equilibrata, gol nel finale",
                "pesoModello": 1
              },
              "goalsFor": 1,
              "goalsAgainst": 0,
              "shotsFor": 15,
              "shotsAgainst": 10,
              "shotsOnTargetFor": 6,
              "shotsOnTargetAgainst": 2,
              "cornersFor": null,
              "cornersAgainst": null,
              "foulsCommitted": 13,
              "foulsDrawn": 8,
              "yellowCards": 1,
              "redCards": 0,
              "possession": null,
              "offsides": null,
              "saves": null,
              "cleanSheets": 1,
              "firstHalfGoalsFor": null,
              "firstHalfGoalsAgainst": null,
              "secondHalfGoalsFor": null,
              "secondHalfGoalsAgainst": null
            }
          ],
          "teamWeightedModel": {
            "matches": 5,
            "weightedGoalsForPerMatch": 1.67,
            "weightedGoalsAgainstPerMatch": 0,
            "weightedShotsForPerMatch": 17.76,
            "weightedShotsAgainstPerMatch": 6.19,
            "weightedShotsOnTargetForPerMatch": 6.4,
            "weightedShotsOnTargetAgainstPerMatch": 1.05,
            "weightedCornersForPerMatch": null,
            "weightedCornersAgainstPerMatch": null,
            "disciplineIndex": 67,
            "attackIndex": 90,
            "defenseIndex": 79,
            "cornerIndex": null,
            "tempoIndex": 80,
            "pressureIndex": 78
          },
          "trends": {
            "lastTwoMatches": {
              "shotsForPerMatch": 19,
              "shotsOnTargetForPerMatch": 8,
              "foulsCommittedPerMatch": 10.5,
              "yellowCardsPerMatch": 0.5
            },
            "knockout": {
              "matches": 2,
              "shotsForPerMatch": 19,
              "shotsOnTargetForPerMatch": 8,
              "foulsCommittedPerMatch": 10.5,
              "yellowCardsPerMatch": 0.5
            }
          },
          "missingFields": [
            "cornersFor",
            "cornersAgainst",
            "possession",
            "saves",
            "firstHalfGoalsFor",
            "firstHalfGoalsAgainst",
            "secondHalfGoalsFor",
            "secondHalfGoalsAgainst"
          ]
        },
        "Belgium": {
          "displayName": "Belgio",
          "sourcePlayerStats": "data/player-stats/spain-belgium-2026-07-10.json",
          "rawMatches": [
            {
              "matchId": "belgium-egypt-2026-06-15",
              "match": "Belgium vs Egypt",
              "opponent": "Egypt",
              "round": "Group stage",
              "matchContext": {
                "tipoPartita": "girone",
                "livelloAvversario": "medio",
                "statoAvversario": "fisico e organizzato",
                "statoGara": "Belgio superiore in girone",
                "pesoModello": 0.62
              },
              "goalsFor": 0,
              "goalsAgainst": 1,
              "shotsFor": 15,
              "shotsAgainst": 14,
              "shotsOnTargetFor": 3,
              "shotsOnTargetAgainst": 3,
              "cornersFor": null,
              "cornersAgainst": null,
              "foulsCommitted": 15,
              "foulsDrawn": 15,
              "yellowCards": 2,
              "redCards": 0,
              "possession": null,
              "offsides": null,
              "saves": null,
              "cleanSheets": 0,
              "firstHalfGoalsFor": null,
              "firstHalfGoalsAgainst": null,
              "secondHalfGoalsFor": null,
              "secondHalfGoalsAgainst": null
            },
            {
              "matchId": "belgium-iran-2026-06-21",
              "match": "Belgium vs Iran",
              "opponent": "Iran",
              "round": "Group stage",
              "matchContext": {
                "tipoPartita": "girone",
                "livelloAvversario": "medio-basso",
                "statoAvversario": "difensivo e compatto",
                "statoGara": "Belgio in gestione territoriale",
                "pesoModello": 0.55
              },
              "goalsFor": 0,
              "goalsAgainst": 0,
              "shotsFor": 23,
              "shotsAgainst": 7,
              "shotsOnTargetFor": 7,
              "shotsOnTargetAgainst": 3,
              "cornersFor": null,
              "cornersAgainst": null,
              "foulsCommitted": 7,
              "foulsDrawn": 8,
              "yellowCards": 1,
              "redCards": 1,
              "possession": null,
              "offsides": null,
              "saves": null,
              "cleanSheets": 1,
              "firstHalfGoalsFor": null,
              "firstHalfGoalsAgainst": null,
              "secondHalfGoalsFor": null,
              "secondHalfGoalsAgainst": null
            },
            {
              "matchId": "new-zealand-belgium-2026-06-26",
              "match": "New Zealand vs Belgium",
              "opponent": "New Zealand",
              "round": "Group stage",
              "matchContext": {
                "tipoPartita": "girone facile con turnover",
                "livelloAvversario": "basso-medio",
                "statoAvversario": "fisico ma inferiore",
                "statoGara": "rotazioni e volume",
                "pesoModello": 0.45
              },
              "goalsFor": 5,
              "goalsAgainst": 1,
              "shotsFor": 35,
              "shotsAgainst": 6,
              "shotsOnTargetFor": 10,
              "shotsOnTargetAgainst": 2,
              "cornersFor": null,
              "cornersAgainst": null,
              "foulsCommitted": 7,
              "foulsDrawn": 10,
              "yellowCards": 0,
              "redCards": 0,
              "possession": null,
              "offsides": null,
              "saves": null,
              "cleanSheets": 0,
              "firstHalfGoalsFor": null,
              "firstHalfGoalsAgainst": null,
              "secondHalfGoalsFor": null,
              "secondHalfGoalsAgainst": null
            },
            {
              "matchId": "belgium-senegal-2026-07-01",
              "match": "Belgium vs Senegal",
              "opponent": "Senegal",
              "round": "Round of 32",
              "matchContext": {
                "tipoPartita": "eliminazione diretta",
                "livelloAvversario": "medio-alto",
                "statoAvversario": "fisico, verticale",
                "statoGara": "gara intensa ai supplementari",
                "pesoModello": 1.1
              },
              "goalsFor": 3,
              "goalsAgainst": 2,
              "shotsFor": 19,
              "shotsAgainst": 19,
              "shotsOnTargetFor": 5,
              "shotsOnTargetAgainst": 5,
              "cornersFor": null,
              "cornersAgainst": null,
              "foulsCommitted": 22,
              "foulsDrawn": 12,
              "yellowCards": 1,
              "redCards": 0,
              "possession": null,
              "offsides": null,
              "saves": null,
              "cleanSheets": 0,
              "firstHalfGoalsFor": null,
              "firstHalfGoalsAgainst": null,
              "secondHalfGoalsFor": null,
              "secondHalfGoalsAgainst": null
            },
            {
              "matchId": "united-states-belgium-2026-07-06",
              "match": "United States vs Belgium",
              "opponent": "United States",
              "round": "Round of 16",
              "matchContext": {
                "tipoPartita": "eliminazione diretta",
                "livelloAvversario": "alto",
                "statoAvversario": "atletico, transizioni rapide",
                "statoGara": "ottavo pesante",
                "pesoModello": 0.9
              },
              "goalsFor": 4,
              "goalsAgainst": 1,
              "shotsFor": 15,
              "shotsAgainst": 7,
              "shotsOnTargetFor": 7,
              "shotsOnTargetAgainst": 2,
              "cornersFor": null,
              "cornersAgainst": null,
              "foulsCommitted": 9,
              "foulsDrawn": 11,
              "yellowCards": 0,
              "redCards": 0,
              "possession": null,
              "offsides": null,
              "saves": null,
              "cleanSheets": 0,
              "firstHalfGoalsFor": null,
              "firstHalfGoalsAgainst": null,
              "secondHalfGoalsFor": null,
              "secondHalfGoalsAgainst": null
            }
          ],
          "teamWeightedModel": {
            "matches": 5,
            "weightedGoalsForPerMatch": 2.53,
            "weightedGoalsAgainstPerMatch": 1.15,
            "weightedShotsForPerMatch": 19.92,
            "weightedShotsAgainstPerMatch": 11.72,
            "weightedShotsOnTargetForPerMatch": 6.08,
            "weightedShotsOnTargetAgainstPerMatch": 3.23,
            "weightedCornersForPerMatch": null,
            "weightedCornersAgainstPerMatch": null,
            "disciplineIndex": 53,
            "attackIndex": 93,
            "defenseIndex": 47,
            "cornerIndex": null,
            "tempoIndex": 100,
            "pressureIndex": 93
          },
          "trends": {
            "lastTwoMatches": {
              "shotsForPerMatch": 17,
              "shotsOnTargetForPerMatch": 6,
              "foulsCommittedPerMatch": 15.5,
              "yellowCardsPerMatch": 0.5
            },
            "knockout": {
              "matches": 2,
              "shotsForPerMatch": 17,
              "shotsOnTargetForPerMatch": 6,
              "foulsCommittedPerMatch": 15.5,
              "yellowCardsPerMatch": 0.5
            }
          },
          "missingFields": [
            "cornersFor",
            "cornersAgainst",
            "possession",
            "saves",
            "firstHalfGoalsFor",
            "firstHalfGoalsAgainst",
            "secondHalfGoalsFor",
            "secondHalfGoalsAgainst"
          ]
        }
      }
    },
    "norway-england-2026-07-11": {
      "match": "Norway-England",
      "teams": {
        "Norway": {
          "displayName": "Norvegia",
          "sourcePlayerStats": "data/player-stats/norway-england-2026-07-11.json",
          "rawMatches": [
            {
              "matchId": "iraq-norway-2026-06-16",
              "match": "Iraq vs Norway",
              "opponent": "Iraq",
              "round": "Group stage",
              "matchContext": {
                "tipoPartita": "girone",
                "livelloAvversario": "basso-medio",
                "statoAvversario": "difensivo e diretto",
                "statoGara": "Norvegia favorita",
                "pesoModello": 0.55
              },
              "goalsFor": 3,
              "goalsAgainst": 1,
              "shotsFor": 12,
              "shotsAgainst": 11,
              "shotsOnTargetFor": 5,
              "shotsOnTargetAgainst": 1,
              "cornersFor": null,
              "cornersAgainst": null,
              "foulsCommitted": 13,
              "foulsDrawn": 11,
              "yellowCards": 0,
              "redCards": 0,
              "possession": null,
              "offsides": null,
              "saves": null,
              "cleanSheets": 0,
              "firstHalfGoalsFor": null,
              "firstHalfGoalsAgainst": null,
              "secondHalfGoalsFor": null,
              "secondHalfGoalsAgainst": null
            },
            {
              "matchId": "norway-senegal-2026-06-22",
              "match": "Norway vs Senegal",
              "opponent": "Senegal",
              "round": "Group stage",
              "matchContext": {
                "tipoPartita": "girone contro avversario forte",
                "livelloAvversario": "medio-alto",
                "statoAvversario": "fisico, verticale",
                "statoGara": "duelli e intensita",
                "pesoModello": 0.7
              },
              "goalsFor": 3,
              "goalsAgainst": 2,
              "shotsFor": 13,
              "shotsAgainst": 16,
              "shotsOnTargetFor": 7,
              "shotsOnTargetAgainst": 4,
              "cornersFor": null,
              "cornersAgainst": null,
              "foulsCommitted": 13,
              "foulsDrawn": 4,
              "yellowCards": 0,
              "redCards": 0,
              "possession": null,
              "offsides": null,
              "saves": null,
              "cleanSheets": 0,
              "firstHalfGoalsFor": null,
              "firstHalfGoalsAgainst": null,
              "secondHalfGoalsFor": null,
              "secondHalfGoalsAgainst": null
            },
            {
              "matchId": "norway-france-2026-06-26",
              "match": "Norway vs France",
              "opponent": "France",
              "round": "Group stage",
              "matchContext": {
                "tipoPartita": "girone contro avversario forte",
                "livelloAvversario": "alto",
                "statoAvversario": "fisica, verticale",
                "statoGara": "gara aperta contro avversario forte",
                "pesoModello": 0.78
              },
              "goalsFor": 1,
              "goalsAgainst": 4,
              "shotsFor": 10,
              "shotsAgainst": 18,
              "shotsOnTargetFor": 4,
              "shotsOnTargetAgainst": 9,
              "cornersFor": null,
              "cornersAgainst": null,
              "foulsCommitted": 9,
              "foulsDrawn": 10,
              "yellowCards": 1,
              "redCards": 0,
              "possession": null,
              "offsides": null,
              "saves": null,
              "cleanSheets": 0,
              "firstHalfGoalsFor": null,
              "firstHalfGoalsAgainst": null,
              "secondHalfGoalsFor": null,
              "secondHalfGoalsAgainst": null
            },
            {
              "matchId": "ivory-coast-norway-2026-06-30",
              "match": "Ivory Coast vs Norway",
              "opponent": "Ivory Coast",
              "round": "Round of 32",
              "matchContext": {
                "tipoPartita": "eliminazione diretta",
                "livelloAvversario": "medio-alto",
                "statoAvversario": "fisico, aggressivo",
                "statoGara": "knockout intenso",
                "pesoModello": 0.82
              },
              "goalsFor": 2,
              "goalsAgainst": 1,
              "shotsFor": 9,
              "shotsAgainst": 14,
              "shotsOnTargetFor": 4,
              "shotsOnTargetAgainst": 5,
              "cornersFor": null,
              "cornersAgainst": null,
              "foulsCommitted": 7,
              "foulsDrawn": 4,
              "yellowCards": 1,
              "redCards": 0,
              "possession": null,
              "offsides": null,
              "saves": null,
              "cleanSheets": 0,
              "firstHalfGoalsFor": null,
              "firstHalfGoalsAgainst": null,
              "secondHalfGoalsFor": null,
              "secondHalfGoalsAgainst": null
            },
            {
              "matchId": "brazil-norway-2026-07-05",
              "match": "Brazil vs Norway",
              "opponent": "Brazil",
              "round": "Round of 16",
              "matchContext": {
                "tipoPartita": "eliminazione diretta",
                "livelloAvversario": "elite",
                "statoAvversario": "tecnico, creativo",
                "statoGara": "ottavo di alto peso",
                "pesoModello": 0.95
              },
              "goalsFor": 2,
              "goalsAgainst": 1,
              "shotsFor": 9,
              "shotsAgainst": 13,
              "shotsOnTargetFor": 5,
              "shotsOnTargetAgainst": 4,
              "cornersFor": null,
              "cornersAgainst": null,
              "foulsCommitted": 6,
              "foulsDrawn": 6,
              "yellowCards": 0,
              "redCards": 0,
              "possession": null,
              "offsides": null,
              "saves": null,
              "cleanSheets": 0,
              "firstHalfGoalsFor": null,
              "firstHalfGoalsAgainst": null,
              "secondHalfGoalsFor": null,
              "secondHalfGoalsAgainst": null
            }
          ],
          "teamWeightedModel": {
            "matches": 5,
            "weightedGoalsForPerMatch": 2.12,
            "weightedGoalsAgainstPerMatch": 1.8,
            "weightedShotsForPerMatch": 10.38,
            "weightedShotsAgainstPerMatch": 14.51,
            "weightedShotsOnTargetForPerMatch": 4.95,
            "weightedShotsOnTargetAgainstPerMatch": 4.81,
            "weightedCornersForPerMatch": null,
            "weightedCornersAgainstPerMatch": null,
            "disciplineIndex": 74,
            "attackIndex": 61,
            "defenseIndex": 27,
            "cornerIndex": null,
            "tempoIndex": 83,
            "pressureIndex": 51
          },
          "trends": {
            "lastTwoMatches": {
              "shotsForPerMatch": 9,
              "shotsOnTargetForPerMatch": 4.5,
              "foulsCommittedPerMatch": 6.5,
              "yellowCardsPerMatch": 0.5
            },
            "knockout": {
              "matches": 2,
              "shotsForPerMatch": 9,
              "shotsOnTargetForPerMatch": 4.5,
              "foulsCommittedPerMatch": 6.5,
              "yellowCardsPerMatch": 0.5
            }
          },
          "missingFields": [
            "cornersFor",
            "cornersAgainst",
            "possession",
            "saves",
            "firstHalfGoalsFor",
            "firstHalfGoalsAgainst",
            "secondHalfGoalsFor",
            "secondHalfGoalsAgainst"
          ]
        },
        "England": {
          "displayName": "Inghilterra",
          "sourcePlayerStats": "data/player-stats/norway-england-2026-07-11.json",
          "rawMatches": [
            {
              "matchId": "england-croatia-2026-06-17",
              "match": "England vs Croatia",
              "opponent": "Croatia",
              "round": "Group stage",
              "matchContext": {
                "tipoPartita": "girone contro avversario forte",
                "livelloAvversario": "medio-alto",
                "statoAvversario": "tecnico, esperto",
                "statoGara": "girone contro rivale solido",
                "pesoModello": 0.7
              },
              "goalsFor": 4,
              "goalsAgainst": 2,
              "shotsFor": 22,
              "shotsAgainst": 10,
              "shotsOnTargetFor": 11,
              "shotsOnTargetAgainst": 5,
              "cornersFor": null,
              "cornersAgainst": null,
              "foulsCommitted": 10,
              "foulsDrawn": 12,
              "yellowCards": 0,
              "redCards": 0,
              "possession": null,
              "offsides": null,
              "saves": null,
              "cleanSheets": 0,
              "firstHalfGoalsFor": null,
              "firstHalfGoalsAgainst": null,
              "secondHalfGoalsFor": null,
              "secondHalfGoalsAgainst": null
            },
            {
              "matchId": "england-ghana-2026-06-23",
              "match": "England vs Ghana",
              "opponent": "Ghana",
              "round": "Group stage",
              "matchContext": {
                "tipoPartita": "girone",
                "livelloAvversario": "medio",
                "statoAvversario": "fisico, verticale",
                "statoGara": "duelli atletici",
                "pesoModello": 0.62
              },
              "goalsFor": 0,
              "goalsAgainst": 0,
              "shotsFor": 19,
              "shotsAgainst": 2,
              "shotsOnTargetFor": 3,
              "shotsOnTargetAgainst": 1,
              "cornersFor": null,
              "cornersAgainst": null,
              "foulsCommitted": 14,
              "foulsDrawn": 24,
              "yellowCards": 1,
              "redCards": 0,
              "possession": null,
              "offsides": null,
              "saves": null,
              "cleanSheets": 1,
              "firstHalfGoalsFor": null,
              "firstHalfGoalsAgainst": null,
              "secondHalfGoalsFor": null,
              "secondHalfGoalsAgainst": null
            },
            {
              "matchId": "panama-england-2026-06-27",
              "match": "Panama vs England",
              "opponent": "Panama",
              "round": "Group stage",
              "matchContext": {
                "tipoPartita": "girone facile con turnover",
                "livelloAvversario": "basso-medio",
                "statoAvversario": "difensivo e inferiore",
                "statoGara": "volume meno predittivo",
                "pesoModello": 0.45
              },
              "goalsFor": 2,
              "goalsAgainst": 0,
              "shotsFor": 17,
              "shotsAgainst": 13,
              "shotsOnTargetFor": 6,
              "shotsOnTargetAgainst": 2,
              "cornersFor": null,
              "cornersAgainst": null,
              "foulsCommitted": 13,
              "foulsDrawn": 16,
              "yellowCards": 1,
              "redCards": 0,
              "possession": null,
              "offsides": null,
              "saves": null,
              "cleanSheets": 1,
              "firstHalfGoalsFor": null,
              "firstHalfGoalsAgainst": null,
              "secondHalfGoalsFor": null,
              "secondHalfGoalsAgainst": null
            },
            {
              "matchId": "england-congo-dr-2026-07-01",
              "match": "England vs Congo DR",
              "opponent": "Congo DR",
              "round": "Round of 32",
              "matchContext": {
                "tipoPartita": "eliminazione diretta",
                "livelloAvversario": "medio",
                "statoAvversario": "fisico, diretto",
                "statoGara": "gestione knockout",
                "pesoModello": 0.8
              },
              "goalsFor": 2,
              "goalsAgainst": 1,
              "shotsFor": 16,
              "shotsAgainst": 7,
              "shotsOnTargetFor": 7,
              "shotsOnTargetAgainst": 2,
              "cornersFor": null,
              "cornersAgainst": null,
              "foulsCommitted": 10,
              "foulsDrawn": 12,
              "yellowCards": 1,
              "redCards": 0,
              "possession": null,
              "offsides": null,
              "saves": null,
              "cleanSheets": 0,
              "firstHalfGoalsFor": null,
              "firstHalfGoalsAgainst": null,
              "secondHalfGoalsFor": null,
              "secondHalfGoalsAgainst": null
            },
            {
              "matchId": "mexico-england-2026-07-05",
              "match": "Mexico vs England",
              "opponent": "Mexico",
              "round": "Round of 16",
              "matchContext": {
                "tipoPartita": "eliminazione diretta",
                "livelloAvversario": "alto",
                "statoAvversario": "tecnico, intenso",
                "statoGara": "ottavo equilibrato",
                "pesoModello": 0.92
              },
              "goalsFor": 3,
              "goalsAgainst": 2,
              "shotsFor": 6,
              "shotsAgainst": 20,
              "shotsOnTargetFor": 5,
              "shotsOnTargetAgainst": 5,
              "cornersFor": null,
              "cornersAgainst": null,
              "foulsCommitted": 7,
              "foulsDrawn": 13,
              "yellowCards": 4,
              "redCards": 1,
              "possession": null,
              "offsides": null,
              "saves": null,
              "cleanSheets": 0,
              "firstHalfGoalsFor": null,
              "firstHalfGoalsAgainst": null,
              "secondHalfGoalsFor": null,
              "secondHalfGoalsAgainst": null
            }
          ],
          "teamWeightedModel": {
            "matches": 5,
            "weightedGoalsForPerMatch": 2.31,
            "weightedGoalsAgainstPerMatch": 1.16,
            "weightedShotsForPerMatch": 15.23,
            "weightedShotsAgainstPerMatch": 10.91,
            "weightedShotsOnTargetForPerMatch": 6.44,
            "weightedShotsOnTargetAgainstPerMatch": 3.21,
            "weightedCornersForPerMatch": null,
            "weightedCornersAgainstPerMatch": null,
            "disciplineIndex": 42,
            "attackIndex": 84,
            "defenseIndex": 49,
            "cornerIndex": null,
            "tempoIndex": 87,
            "pressureIndex": 92
          },
          "trends": {
            "lastTwoMatches": {
              "shotsForPerMatch": 11,
              "shotsOnTargetForPerMatch": 6,
              "foulsCommittedPerMatch": 8.5,
              "yellowCardsPerMatch": 2.5
            },
            "knockout": {
              "matches": 2,
              "shotsForPerMatch": 11,
              "shotsOnTargetForPerMatch": 6,
              "foulsCommittedPerMatch": 8.5,
              "yellowCardsPerMatch": 2.5
            }
          },
          "missingFields": [
            "cornersFor",
            "cornersAgainst",
            "possession",
            "saves",
            "firstHalfGoalsFor",
            "firstHalfGoalsAgainst",
            "secondHalfGoalsFor",
            "secondHalfGoalsAgainst"
          ]
        }
      }
    },
    "argentina-switzerland-2026-07-11": {
      "match": "Argentina-Switzerland",
      "teams": {
        "Argentina": {
          "displayName": "Argentina",
          "sourcePlayerStats": "data/player-stats/argentina-switzerland-2026-07-11.json",
          "rawMatches": [
            {
              "matchId": "argentina-algeria-2026-06-16",
              "match": "Argentina vs Algeria",
              "opponent": "Algeria",
              "round": "Group stage",
              "matchContext": {
                "tipoPartita": "girone",
                "livelloAvversario": "medio",
                "statoAvversario": "fisico e organizzato",
                "statoGara": "Argentina favorita",
                "pesoModello": 0.62
              },
              "goalsFor": 3,
              "goalsAgainst": 0,
              "shotsFor": 10,
              "shotsAgainst": 7,
              "shotsOnTargetFor": 6,
              "shotsOnTargetAgainst": 0,
              "cornersFor": null,
              "cornersAgainst": null,
              "foulsCommitted": 13,
              "foulsDrawn": 7,
              "yellowCards": 0,
              "redCards": 0,
              "possession": null,
              "offsides": null,
              "saves": null,
              "cleanSheets": 1,
              "firstHalfGoalsFor": null,
              "firstHalfGoalsAgainst": null,
              "secondHalfGoalsFor": null,
              "secondHalfGoalsAgainst": null
            },
            {
              "matchId": "argentina-austria-2026-06-22",
              "match": "Argentina vs Austria",
              "opponent": "Austria",
              "round": "Group stage",
              "matchContext": {
                "tipoPartita": "girone contro avversario forte",
                "livelloAvversario": "medio-alto",
                "statoAvversario": "fisico, organizzato",
                "statoGara": "test intensita",
                "pesoModello": 0.7
              },
              "goalsFor": 2,
              "goalsAgainst": 0,
              "shotsFor": 12,
              "shotsAgainst": 6,
              "shotsOnTargetFor": 5,
              "shotsOnTargetAgainst": 1,
              "cornersFor": null,
              "cornersAgainst": null,
              "foulsCommitted": 13,
              "foulsDrawn": 12,
              "yellowCards": 2,
              "redCards": 0,
              "possession": null,
              "offsides": null,
              "saves": null,
              "cleanSheets": 1,
              "firstHalfGoalsFor": null,
              "firstHalfGoalsAgainst": null,
              "secondHalfGoalsFor": null,
              "secondHalfGoalsAgainst": null
            },
            {
              "matchId": "jordan-argentina-2026-06-27",
              "match": "Jordan vs Argentina",
              "opponent": "Jordan",
              "round": "Group stage",
              "matchContext": {
                "tipoPartita": "girone facile con turnover",
                "livelloAvversario": "basso-medio",
                "statoAvversario": "difensivo e inferiore",
                "statoGara": "volume meno predittivo",
                "pesoModello": 0.45
              },
              "goalsFor": 3,
              "goalsAgainst": 1,
              "shotsFor": 12,
              "shotsAgainst": 5,
              "shotsOnTargetFor": 4,
              "shotsOnTargetAgainst": 1,
              "cornersFor": null,
              "cornersAgainst": null,
              "foulsCommitted": 7,
              "foulsDrawn": 12,
              "yellowCards": 0,
              "redCards": 0,
              "possession": null,
              "offsides": null,
              "saves": null,
              "cleanSheets": 0,
              "firstHalfGoalsFor": null,
              "firstHalfGoalsAgainst": null,
              "secondHalfGoalsFor": null,
              "secondHalfGoalsAgainst": null
            },
            {
              "matchId": "argentina-cape-verde-2026-07-03",
              "match": "Argentina vs Cape Verde",
              "opponent": "Cape Verde",
              "round": "Round of 32",
              "matchContext": {
                "tipoPartita": "eliminazione diretta",
                "livelloAvversario": "medio-basso",
                "statoAvversario": "difensivo, blocco basso",
                "statoGara": "supplementari",
                "pesoModello": 1.05
              },
              "goalsFor": 2,
              "goalsAgainst": 2,
              "shotsFor": 22,
              "shotsAgainst": 16,
              "shotsOnTargetFor": 10,
              "shotsOnTargetAgainst": 5,
              "cornersFor": null,
              "cornersAgainst": null,
              "foulsCommitted": 13,
              "foulsDrawn": 12,
              "yellowCards": 1,
              "redCards": 0,
              "possession": null,
              "offsides": null,
              "saves": null,
              "cleanSheets": 0,
              "firstHalfGoalsFor": null,
              "firstHalfGoalsAgainst": null,
              "secondHalfGoalsFor": null,
              "secondHalfGoalsAgainst": null
            },
            {
              "matchId": "argentina-egypt-2026-07-07",
              "match": "Argentina vs Egypt",
              "opponent": "Egypt",
              "round": "Round of 16",
              "matchContext": {
                "tipoPartita": "eliminazione diretta",
                "livelloAvversario": "medio",
                "statoAvversario": "fisico, organizzato",
                "statoGara": "ottavo controllato",
                "pesoModello": 0.9
              },
              "goalsFor": 3,
              "goalsAgainst": 2,
              "shotsFor": 19,
              "shotsAgainst": 5,
              "shotsOnTargetFor": 7,
              "shotsOnTargetAgainst": 2,
              "cornersFor": null,
              "cornersAgainst": null,
              "foulsCommitted": 13,
              "foulsDrawn": 11,
              "yellowCards": 0,
              "redCards": 0,
              "possession": null,
              "offsides": null,
              "saves": null,
              "cleanSheets": 0,
              "firstHalfGoalsFor": null,
              "firstHalfGoalsAgainst": null,
              "secondHalfGoalsFor": null,
              "secondHalfGoalsAgainst": null
            }
          ],
          "teamWeightedModel": {
            "matches": 5,
            "weightedGoalsForPerMatch": 2.53,
            "weightedGoalsAgainstPerMatch": 1.17,
            "weightedShotsForPerMatch": 16.18,
            "weightedShotsAgainstPerMatch": 8.63,
            "weightedShotsOnTargetForPerMatch": 6.94,
            "weightedShotsOnTargetAgainstPerMatch": 2.2,
            "weightedCornersForPerMatch": null,
            "weightedCornersAgainstPerMatch": null,
            "disciplineIndex": 64,
            "attackIndex": 90,
            "defenseIndex": 61,
            "cornerIndex": null,
            "tempoIndex": 83,
            "pressureIndex": 81
          },
          "trends": {
            "lastTwoMatches": {
              "shotsForPerMatch": 20.5,
              "shotsOnTargetForPerMatch": 8.5,
              "foulsCommittedPerMatch": 13,
              "yellowCardsPerMatch": 0.5
            },
            "knockout": {
              "matches": 2,
              "shotsForPerMatch": 20.5,
              "shotsOnTargetForPerMatch": 8.5,
              "foulsCommittedPerMatch": 13,
              "yellowCardsPerMatch": 0.5
            }
          },
          "missingFields": [
            "cornersFor",
            "cornersAgainst",
            "possession",
            "saves",
            "firstHalfGoalsFor",
            "firstHalfGoalsAgainst",
            "secondHalfGoalsFor",
            "secondHalfGoalsAgainst"
          ]
        },
        "Switzerland": {
          "displayName": "Svizzera",
          "sourcePlayerStats": "data/player-stats/argentina-switzerland-2026-07-11.json",
          "rawMatches": [
            {
              "matchId": "qatar-switzerland-2026-06-13",
              "match": "Qatar vs Switzerland",
              "opponent": "Qatar",
              "round": "Group stage",
              "matchContext": {
                "tipoPartita": "girone",
                "livelloAvversario": "medio-basso",
                "statoAvversario": "difensivo, organizzato",
                "statoGara": "Svizzera favorita",
                "pesoModello": 0.55
              },
              "goalsFor": 1,
              "goalsAgainst": 0,
              "shotsFor": 26,
              "shotsAgainst": 6,
              "shotsOnTargetFor": 7,
              "shotsOnTargetAgainst": 3,
              "cornersFor": null,
              "cornersAgainst": null,
              "foulsCommitted": 11,
              "foulsDrawn": 12,
              "yellowCards": 1,
              "redCards": 0,
              "possession": null,
              "offsides": null,
              "saves": null,
              "cleanSheets": 1,
              "firstHalfGoalsFor": null,
              "firstHalfGoalsAgainst": null,
              "secondHalfGoalsFor": null,
              "secondHalfGoalsAgainst": null
            },
            {
              "matchId": "switzerland-bosnia-herzegovina-2026-06-18",
              "match": "Switzerland vs Bosnia-Herzegovina",
              "opponent": "Bosnia-Herzegovina",
              "round": "Group stage",
              "matchContext": {
                "tipoPartita": "girone",
                "livelloAvversario": "medio",
                "statoAvversario": "fisico e diretto",
                "statoGara": "girone competitivo",
                "pesoModello": 0.62
              },
              "goalsFor": 4,
              "goalsAgainst": 1,
              "shotsFor": 13,
              "shotsAgainst": 5,
              "shotsOnTargetFor": 7,
              "shotsOnTargetAgainst": 3,
              "cornersFor": null,
              "cornersAgainst": null,
              "foulsCommitted": 7,
              "foulsDrawn": 17,
              "yellowCards": 1,
              "redCards": 0,
              "possession": null,
              "offsides": null,
              "saves": null,
              "cleanSheets": 0,
              "firstHalfGoalsFor": null,
              "firstHalfGoalsAgainst": null,
              "secondHalfGoalsFor": null,
              "secondHalfGoalsAgainst": null
            },
            {
              "matchId": "switzerland-canada-2026-06-24",
              "match": "Switzerland vs Canada",
              "opponent": "Canada",
              "round": "Group stage",
              "matchContext": {
                "tipoPartita": "girone contro avversario forte",
                "livelloAvversario": "medio-alto",
                "statoAvversario": "atletico, verticale",
                "statoGara": "test transizioni",
                "pesoModello": 0.7
              },
              "goalsFor": 2,
              "goalsAgainst": 1,
              "shotsFor": 6,
              "shotsAgainst": 13,
              "shotsOnTargetFor": 4,
              "shotsOnTargetAgainst": 7,
              "cornersFor": null,
              "cornersAgainst": null,
              "foulsCommitted": 19,
              "foulsDrawn": 13,
              "yellowCards": 1,
              "redCards": 0,
              "possession": null,
              "offsides": null,
              "saves": null,
              "cleanSheets": 0,
              "firstHalfGoalsFor": null,
              "firstHalfGoalsAgainst": null,
              "secondHalfGoalsFor": null,
              "secondHalfGoalsAgainst": null
            },
            {
              "matchId": "switzerland-algeria-2026-07-02",
              "match": "Switzerland vs Algeria",
              "opponent": "Algeria",
              "round": "Round of 32",
              "matchContext": {
                "tipoPartita": "eliminazione diretta",
                "livelloAvversario": "medio",
                "statoAvversario": "fisico, compatto",
                "statoGara": "knockout controllato",
                "pesoModello": 0.8
              },
              "goalsFor": 2,
              "goalsAgainst": 0,
              "shotsFor": 11,
              "shotsAgainst": 8,
              "shotsOnTargetFor": 5,
              "shotsOnTargetAgainst": 2,
              "cornersFor": null,
              "cornersAgainst": null,
              "foulsCommitted": 10,
              "foulsDrawn": 12,
              "yellowCards": 0,
              "redCards": 0,
              "possession": null,
              "offsides": null,
              "saves": null,
              "cleanSheets": 1,
              "firstHalfGoalsFor": null,
              "firstHalfGoalsAgainst": null,
              "secondHalfGoalsFor": null,
              "secondHalfGoalsAgainst": null
            },
            {
              "matchId": "switzerland-colombia-2026-07-07",
              "match": "Switzerland vs Colombia",
              "opponent": "Colombia",
              "round": "Round of 16",
              "matchContext": {
                "tipoPartita": "eliminazione diretta",
                "livelloAvversario": "alto",
                "statoAvversario": "tecnico, creativo",
                "statoGara": "ottavo equilibrato ai rigori",
                "pesoModello": 1
              },
              "goalsFor": 0,
              "goalsAgainst": 0,
              "shotsFor": 7,
              "shotsAgainst": 15,
              "shotsOnTargetFor": 2,
              "shotsOnTargetAgainst": 3,
              "cornersFor": null,
              "cornersAgainst": null,
              "foulsCommitted": 22,
              "foulsDrawn": 21,
              "yellowCards": 3,
              "redCards": 0,
              "possession": null,
              "offsides": null,
              "saves": null,
              "cleanSheets": 1,
              "firstHalfGoalsFor": null,
              "firstHalfGoalsAgainst": null,
              "secondHalfGoalsFor": null,
              "secondHalfGoalsAgainst": null
            }
          ],
          "teamWeightedModel": {
            "matches": 5,
            "weightedGoalsForPerMatch": 1.64,
            "weightedGoalsAgainstPerMatch": 0.36,
            "weightedShotsForPerMatch": 11.54,
            "weightedShotsAgainstPerMatch": 10.05,
            "weightedShotsOnTargetForPerMatch": 4.63,
            "weightedShotsOnTargetAgainstPerMatch": 3.54,
            "weightedCornersForPerMatch": null,
            "weightedCornersAgainstPerMatch": null,
            "disciplineIndex": 47,
            "attackIndex": 62,
            "defenseIndex": 53,
            "cornerIndex": null,
            "tempoIndex": 72,
            "pressureIndex": 84
          },
          "trends": {
            "lastTwoMatches": {
              "shotsForPerMatch": 9,
              "shotsOnTargetForPerMatch": 3.5,
              "foulsCommittedPerMatch": 16,
              "yellowCardsPerMatch": 1.5
            },
            "knockout": {
              "matches": 2,
              "shotsForPerMatch": 9,
              "shotsOnTargetForPerMatch": 3.5,
              "foulsCommittedPerMatch": 16,
              "yellowCardsPerMatch": 1.5
            }
          },
          "missingFields": [
            "cornersFor",
            "cornersAgainst",
            "possession",
            "saves",
            "firstHalfGoalsFor",
            "firstHalfGoalsAgainst",
            "secondHalfGoalsFor",
            "secondHalfGoalsAgainst"
          ]
        }
      }
    }
  }
}
